everypolitician/__init__.py
everypolitician/lib.py
everypolitician-0.0.13.dist-info/DESCRIPTION.rst
everypolitician-0.0.13.dist-info/METADATA
everypolitician-0.0.13.dist-info/RECORD
everypolitician-0.0.13.dist-info/WHEEL
everypolitician-0.0.13.dist-info/metadata.json
everypolitician-0.0.13.dist-info/top_level.txt
