Metadata-Version: 2.0
Name: everypolitician
Version: 0.0.13
Summary: Navigate countries and legislatures from EveryPolitician
Home-page: UNKNOWN
Author: Mark Longair
Author-email: mark@mysociety.org
License: AGPL
Keywords: politics data civic-tech
Platform: UNKNOWN
Requires-Dist: requests
Requires-Dist: six (>=1.9.0)
Requires-Dist: everypolitician-popolo (>=0.0.11)
